setup.py
django_project_template_loader.egg-info/PKG-INFO
django_project_template_loader.egg-info/SOURCES.txt
django_project_template_loader.egg-info/dependency_links.txt
django_project_template_loader.egg-info/top_level.txt
project_template_loader/__init__.py
project_template_loader/loaders/__init__.py
project_template_loader/loaders/project_directory.py