Metadata-Version: 1.0
Name: django-project-template-loader
Version: 0.1.2
Summary: An app to provide a template loader which pulls templates from [project_dir]/templates
Home-page: http://bitbucket.org/cliff/django-project-template-loader/
Author: J. Cliff Dyer
Author-email: jcd@sdf.lonestar.org
License: UNKNOWN
Platform: UNKNOWN
Classifier: Development Status :: 4 - Beta
Classifier: Environment :: Web Environment
Classifier: Framework :: Django
Classifier: Intended Audience :: Developers
Classifier: License :: OSI Approved :: MIT License
Classifier: Operating System :: OS Independent
Classifier: Programming Language :: Python
Classifier: Programming Language :: Python :: 2
Classifier: Topic :: Internet :: WWW/HTTP :: Site Management
Classifier: Topic :: Utilities
